five_one_one/__init__.py
five_one_one/df_utils.py
five_one_one/nlp_utils.py
five_one_one-1.2.2.dist-info/LICENSE
five_one_one-1.2.2.dist-info/METADATA
five_one_one-1.2.2.dist-info/WHEEL
five_one_one-1.2.2.dist-info/top_level.txt
five_one_one-1.2.2.dist-info/RECORD
