Metadata-Version: 2.1
Name: five-one-one
Version: 1.2.2
Summary: a collection of data science helper functions
Home-page: https://datascience.stromsy.com
Author: ecowley
Author-email: erik@stromsy.com
License: UNKNOWN
Platform: UNKNOWN
Classifier: Programming Language :: Python :: 3
Classifier: License :: OSI Approved :: MIT License
Classifier: Operating System :: OS Independent
Requires-Python: >=3.7
Requires-Dist: numpy
Requires-Dist: pandas
Requires-Dist: spacy
